{
	"Name": "Lynny Knits",
	"Description": "Create images for social media posts",
	"StartingCanvasWidth": 500,
	"StartingCanvasHeight": 500,
	"FastEffects": false,
	"Inputs": {
	},
	"Outputs": [
		{
			"OutputName": "500x500",
			"OutputFileType": "png",
			"Width": 500,
			"Height": 500
		},
		{
			"OutputName": "250x500",
			"OutputFileType": "png",
			"Width": 250,
			"Height": 500
		},
		{
			"OutputName": "500x250",
			"OutputFileType": "png",
			"Width": 500,
			"Height": 250
		},
		{
			"OutputName": "250x250",
			"OutputFileType": "png",
			"Width": 250,
			"Height": 250
		}
	],
	"Layers": {
		"Price": {
			"Alpha": 1,
			"Image": null,
			"ResizePivotX": 1,
			"ResizePivotY": 1,
			"ResizeWidth": 0.1,
			"ResizeHeight": 0.1,
			"Effects": [
				{
					"Type": "Noise"
				}
			],
			"Actions": [
				{
					"Type": "SelectTool",
					"ToolId": "Text_Tool"
				},
				{
					"Type": "SetColour",
					"ColourR": 255,
					"ColourG": 255,
					"ColourB": 255
				},
				{
					"Type": "MousePos",
					"PixelsX": 450,
					"PixelsY": 500
				},
				{
					"Type": "MouseDown"
				},
				{
					"Type": "MouseUp"
				},
				{
					"Type": "Keys",
					"Keys": "£5.35"
				},
				{
					"Type": "SelectTool",
					"ToolId": "Freehand_Tool"
				}
			]
		},
		"BlackBoard": {
			"Alpha": 1,
			"Image": "Templates/LynnyKnits/BlackBoard.png",
			"ResizePivotX": 1,
			"ResizePivotY": 1,
			"ResizeWidth": 0.1,
			"ResizeHeight": 0.1,
			"Effects": [
			]
		},
		"WaterMark": {
			"Alpha": 0.1,
			"Image": "Templates/Louie_Watermark.png",
			"ResizePivotX": 0.5,
			"ResizePivotY": 0.5,
			"ResizeWidth": 1,
			"ResizeHeight": 1,
			"Effects": [
			]
		},
		"Product": {
			"Alpha": 1,
			"Image": "Templates/product_example.jpg",
			"ResizePivotX": 0.5,
			"ResizePivotY": 0.5,
			"Effects": [
			]
		}
	}
}